setup.py
QueryVin/__init__.py
QueryVin/query_service.py
QueryVin.egg-info/PKG-INFO
QueryVin.egg-info/SOURCES.txt
QueryVin.egg-info/dependency_links.txt
QueryVin.egg-info/not-zip-safe
QueryVin.egg-info/requires.txt
QueryVin.egg-info/top_level.txt