Metadata-Version: 1.0
Name: QueryVin
Version: 0.0.1
Summary: query vin information
Home-page: https://github.com/fiveddd/QueryVin
Author: FiveDDD
Author-email: lhorvce@hotmail.com
License: MIT License
Platform: UNKNOWN
